{
    "projects": [
        {
            "image": "",
            "title": "TensorFlow based Object Detection System",
            "bodyText": "- Developed a real-time object detection model with 90% accuracy.\n - Utilized YOLOv4 for diverse object identification tasks.\n - Improved processing speed by optimizing TensorFlow and GPU usage.",
            "links": [
                {
                    "text": "GitHub",
                    "href": "https://github.com/malak29/object-recognition-project"
                }
            ],
            "tags": [
                "TensorFlow",
                "OpenCV",
                "Docker",
                "Kubernetes",
                "Python",
                "Numpy",
                "Pandas"
            ]
        },
        {
            "image": "",
            "title": "Deep Learning Handwriting Analytics",
            "bodyText": "- Created a handwriting recognition system with 92% character recognition accuracy.\n - Implemented LSTM networks for sequential data analysis.\n - Deployed the model using Flask with React frontend.",
            "links": [
                {
                    "text": "GitHub",
                    "href": "https://github.com/malak29/handwriting-analysis"
                }
            ],
            "tags": [
                "TensorFlow",
                "Keras",
                "LSTM",
                "Flask",
                "React",
                "Python",
                "Pandas",
                "Numpy"
            ]
        },
        {
            "image": "",
            "title": "Predictive Heart Attack Risk Analytics",
            "bodyText": "- Built a model predicting heart attack risks, reducing hospitalizations by 25%.\n - Applied Gradient Boosting and SHAP for interpretability.\n - Integrated with Tableau dashboards and a Django web application.",
            "links": [
                {
                    "text": "GitHub",
                    "href": "https://github.com/mayankagarwal09/Caaring"
                }
            ],
            "tags": [
                "Gradient Boosting",
                "SHAP",
                "Tableau",
                "React",
                "Django",
                "Python",
                "Scikit-learn",
                "Pandas"
            ]
        },
        {
            "image": "",
            "title": "Electric Vehicle Population Analytics",
            "bodyText": "- Analyzed EV adoption patterns, predicting a 30% increase in five years.\n - Used clustering and regression models on large datasets.\n - Visualized results through Power BI, supporting policy-making decisions.",
            "links": [
                {
                    "text": "GitHub",
                    "href": "https://github.com/malak29/electric-vehicle-population-analysis"
                }
            ],
            "tags": [
                "K-means Clustering",
                "Linear Regression",
                "Power BI",
                "Python",
                "Pandas",
                "Numpy",
                "Scikit-learn",
                "Flask"
            ]
        },
        {
            "image": "",
            "title": "Boston Check Book Analytics",
            "bodyText": "- Conducted financial data analysis, improving budget efficiency by 15%.\n - Leveraged PySpark for big data processing and insights.\n - Created interactive Tableau dashboards, deployed via Django.",
            "links": [],
            "tags": [
                "PySpark",
                "Tableau",
                "Django",
                "Python",
                "Pandas",
                "Numpy",
                "Hadoop",
                "SQL"
            ]
        },
        {
            "image": "",
            "title": "Elderly Mediclaim Analytics",
            "bodyText": "- Optimized mediclaim approvals, reducing processing time by 40%.\n - Utilized Random Forest and logistic regression on historical data.\n - Deployed Flask API with React user interface.",
            "links": [],
            "tags": [
                "Random Forest",
                "Logistic Regression",
                "Flask",
                "React",
                "Python",
                "Scikit-learn",
                "Pandas",
                "Numpy"
            ]
        },
        {
            "image": "",
            "title": "Federated Learning for Hospital Branches",
            "bodyText": "- Implemented federated learning, enhancing prediction accuracy by 12% across hospitals.\n - Maintained data privacy using secure aggregation techniques.\n - Coordinated model training with PySyft and PyTorch.",
            "links": [],
            "tags": [
                "Federated Learning",
                "PySyft",
                "PyTorch",
                "Docker",
                "Kubernetes",
                "Python",
                "Pandas",
                "Numpy"
            ]
        }
    ]
}